libsegfault.dll
libsegfault.so
segfault/__init__.py
segfault/segfault.py
segfault_package-0.0.3.dist-info/METADATA
segfault_package-0.0.3.dist-info/WHEEL
segfault_package-0.0.3.dist-info/top_level.txt
segfault_package-0.0.3.dist-info/RECORD
