Metadata-Version: 2.1
Name: segfault-package
Version: 0.0.3
Summary: If you ever missed segfaults in Python, there you go
Home-page: https://github.com/fdmx2301/segfault.git
Author: pael
Requires-Python: >=3.6
